mpl_fold_axis.py
mpl_fold_axis-0.1.1.dist-info/LICENSE
mpl_fold_axis-0.1.1.dist-info/METADATA
mpl_fold_axis-0.1.1.dist-info/WHEEL
mpl_fold_axis-0.1.1.dist-info/top_level.txt
mpl_fold_axis-0.1.1.dist-info/RECORD
