Metadata-Version: 2.2
Name: mpl_fold_axis
Version: 0.1.1
Summary: A short description of your package
Home-page: https://github.com/wuyao1997/mpl_fold_axis
Author: Wu Yao
Author-email: wuyao@qq.com
Classifier: Programming Language :: Python :: 3
Classifier: License :: OSI Approved :: MIT License
Classifier: Operating System :: OS Independent
Requires-Python: >=3.6
License-File: LICENSE
Requires-Dist: matplotlib>=3.0.0
Dynamic: author
Dynamic: author-email
Dynamic: classifier
Dynamic: description
Dynamic: description-content-type
Dynamic: home-page
Dynamic: requires-dist
Dynamic: requires-python
Dynamic: summary
